{
    "data": [
        {
            "date": "2026-04-14",
            "title": "User Experience and Early Clinical Outcomes of a Mental Wellness Chatbot for Depression and Anxiety: Pilot Evaluation Mixed Methods Study",
            "url": "https://pubmed.ncbi.nlm.nih.gov/41980262/?utm_source=Other&utm_medium=rss&utm_campaign=pubmed-2&utm_content=1hSsbZPB1F1mLEy6VDSKtqfkJFqlED_Lgw_HOIW51blP7O7Mst&fc=20210826060919&ff=20260414210029&v=2.19.0.post6+133c1fe",
            "source": "PubMed"
        },
        {
            "date": "2026-04-14",
            "title": "Nurses' Evaluation of a Service Robot for Inpatient Care: Technology Acceptance Study",
            "url": "https://pubmed.ncbi.nlm.nih.gov/41980241/?utm_source=Other&utm_medium=rss&utm_campaign=pubmed-2&utm_content=1hSsbZPB1F1mLEy6VDSKtqfkJFqlED_Lgw_HOIW51blP7O7Mst&fc=20210826060919&ff=20260414210029&v=2.19.0.post6+133c1fe",
            "source": "PubMed"
        },
        {
            "date": "2026-04-14",
            "title": "Development of Virtual Mental Health Stepped Care Service for a Heart Failure Remote Management Program: Qualitative Descriptive Study",
            "url": "https://pubmed.ncbi.nlm.nih.gov/41980201/?utm_source=Other&utm_medium=rss&utm_campaign=pubmed-2&utm_content=1hSsbZPB1F1mLEy6VDSKtqfkJFqlED_Lgw_HOIW51blP7O7Mst&fc=20210826060919&ff=20260414210029&v=2.19.0.post6+133c1fe",
            "source": "PubMed"
        }
    ],
    "date": "1776214826565",
    "latestUpdate": "Uppdaterades senast vid: 2026-04-15 03:00",
    "source": "Information är tagen från PubMed RSS flöde. Information tillhör PubMed."
}